pygid/__init__.py
pygid/conversion.py
pygid/coordmaps.py
pygid/dataloader.py
pygid/datasaver.py
pygid/expparams.py
pygid/nexus_reader.py
pygid/pixel_dict.py
pygid/visualization.py
pygid-0.2.3.dist-info/licenses/LICENSE
tests/__init__.py
tests/test_conversion.py
tests/test_coordmaps.py
tests/test_expparams.py
pygid-0.2.3.dist-info/METADATA
pygid-0.2.3.dist-info/WHEEL
pygid-0.2.3.dist-info/top_level.txt
pygid-0.2.3.dist-info/RECORD
